rtl/fifo.v
module fifo #(  parameter DATA_WIDTH = 8 ,
                parameter DEPTH = 16)(
                    input wire clk,
                    input wire rst,

                    input wire wr_en,
                    input wire rd_en,

                    input wire [DATA_WIDTH-1:0] din,

                    output reg [DATA_WIDTH-1:0] dout,
                    
                    output wire full,
                    output wire empty,

                    output reg overflow,
                    output reg underflow

                );
    /*
        INTERNAL MEMORY
    */
    
    reg [DATA_WIDTH-1:0] memory [0:DEPTH-1];    
   
    /*
        INTERNAL REGISTERS
    */
    
    localparam ADDR_WIDTH = $clog2(DEPTH);

    reg [ADDR_WIDTH-1:0] wr_ptr;//write pointer
    reg [ADDR_WIDTH-1:0] rd_ptr;//read pointer

    reg [ADDR_WIDTH:0] count;

    /*
        NEXT STATE 
    */

    wire [ADDR_WIDTH-1:0] wr_ptr_next;
    wire [ADDR_WIDTH-1:0] rd_ptr_next;
    
    assign wr_ptr_next = (wr_ptr == DEPTH-1) ? 0 : wr_ptr + 1;
    assign rd_ptr_next = (rd_ptr == DEPTH-1) ? 0 : rd_ptr + 1;

    /*
        STATUS FLAGS
    */

    assign full = (count == DEPTH);
    assign empty = (count == 0);

    /*
        OPERATION ENABLE LOGIC
    */

    wire write_ok;
    wire read_ok;

    assign write_ok = wr_en && (!full || rd_en);
    assign read_ok  = rd_en && !empty;


    /*
        SEQUENTIAL LOGIC SECTION
    */
    always@(posedge clk) begin

        if (rst) begin

            wr_ptr <= 0;
            rd_ptr <= 0;
            count <= 0;

            dout <= 0;

            overflow <= 0;
            underflow <= 0;

        end
        else begin
            overflow <= 0;
            underflow <= 0;
            /*
                WRITE OPERATION
            */
            if (wr_en) begin
                if (write_ok) begin

                    memory[wr_ptr] <= din;
                    wr_ptr <= wr_ptr_next;

                end
                else if (wr_en) begin

                    overflow <= 1;

                end
            end
            /*
                READ OPERATION
            */
            if (rd_en) begin
                if (read_ok) begin

                    dout <= memory[rd_ptr];
                    rd_ptr <= rd_ptr_next;

                end
                else if (rd_en) begin

                    underflow <= 1;

                end
            end
            /*
                COUNT UPDATE
            */
            if (write_ok && !read_ok)
                count <= count + 1;
            else if (!write_ok && read_ok)
                count <= count - 1;
        end
    end

endmodule

tb/fifo_tb_underflow.v
    `timescale 1ns/1ps

    module fifo_tb_underflow;

        /*
            ALL DECLARATIONS
        */
        parameter DATA_WIDTH = 8;
        parameter DEPTH = 16;

        reg clk;
        reg rst;

        reg wr_en;
        reg rd_en;

        reg [DATA_WIDTH-1:0] din;

        wire [DATA_WIDTH-1:0] dout;
                        
        wire full;
        wire empty;

        wire overflow;
        wire underflow;

        fifo #(
            .DATA_WIDTH(DATA_WIDTH),
            .DEPTH(DEPTH)
        ) dut (

            .clk(clk),
            .rst(rst),

            .wr_en(wr_en),  
            .rd_en(rd_en),

            .din(din),
            .dout(dout),

            .full(full),
            .empty(empty),

            .overflow(overflow),
            .underflow(underflow)

        );

        initial begin
            clk = 0;
        end

        /*
            CLK GENERATION
        */
        always #5 clk = ~clk;
        /*
            RESET INITIATION
        */
        initial begin

            $dumpfile("wave/fifo_underflow.vcd");
            $dumpvars(0,fifo_tb_underflow);

            rst  = 1;
            wr_en = 0;
            rd_en = 0;
            din = 0;

            #20;//2 clk cycles

            rst = 0; 

            //1st write
            #10;
            
            din = 8'h11;
            wr_en = 1;

            #10;//one cycle

            wr_en = 0;

            
             //1st read
            #10;
            rd_en = 1;

            #10;
            rd_en = 0;

            //2nd read
            #10;
            rd_en = 1;

            #10;
            rd_en = 0;

            //3rd read
            #10;
            rd_en = 1;

            #10;
            rd_en = 0;

            //END
            #20;
            $finish;//signals would run forever otherwise

        end
        

    endmodule

wave/fifo.vcd
$date
	Mon Jul 13 21:32:51 2026
$end
$version
	Icarus Verilog
$end
$timescale
	1ps
$end
$scope module fifo_tb_underflow $end
$var wire 1 ! underflow $end
$var wire 1 " overflow $end
$var wire 1 # full $end
$var wire 1 $ empty $end
$var wire 8 % dout [7:0] $end
$var parameter 32 & DATA_WIDTH $end
$var parameter 32 ' DEPTH $end
$var reg 1 ( clk $end
$var reg 8 ) din [7:0] $end
$var reg 1 * rd_en $end
$var reg 1 + rst $end
$var reg 1 , wr_en $end
$scope module dut $end
$var wire 1 ( clk $end
$var wire 8 - din [7:0] $end
$var wire 1 * rd_en $end
$var wire 1 . read_ok $end
$var wire 1 + rst $end
$var wire 1 , wr_en $end
$var wire 1 / write_ok $end
$var wire 4 0 wr_ptr_next [3:0] $end
$var wire 4 1 rd_ptr_next [3:0] $end
$var wire 1 # full $end
$var wire 1 $ empty $end
$var parameter 32 2 ADDR_WIDTH $end
$var parameter 32 3 DATA_WIDTH $end
$var parameter 32 4 DEPTH $end
$var reg 5 5 count [4:0] $end
$var reg 8 6 dout [7:0] $end
$var reg 1 " overflow $end
$var reg 4 7 rd_ptr [3:0] $end
$var reg 1 ! underflow $end
$var reg 4 8 wr_ptr [3:0] $end
$upscope $end
$upscope $end
$enddefinitions $end
$comment Show the parameter values. $end
$dumpall
b10000 4
b1000 3
b100 2
b10000 '
b1000 &
$end
#0
$dumpvars
bx 8
bx 7
bx 6
bx 5
bx 1
bx 0
0/
0.
b0 -
0,
1+
0*
b0 )
0(
bx %
x$
x#
x"
x!
$end
#5000
b1 1
b1 0
0!
0"
b0 %
b0 6
0#
1$
b0 5
b0 7
b0 8
1(
#10000
0(
#15000
1(
#20000
0(
0+
#25000
1(
#30000
1/
0(
1,
b10001 )
b10001 -
#35000
b10 0
0$
b1 5
b1 8
1(
#40000
0/
0(
0,
#45000
1(
#50000
1.
0(
1*
#55000
0.
b10 1
1$
b0 5
b1 7
b10001 %
b10001 6
1(
#60000
0(
0*
#65000
1(
#70000
0(
1*
#75000
1!
1(
#80000
0(
0*
#85000
0!
1(
#90000
0(
1*
#95000
1!
1(
#100000
0(
0*
#105000
0!
1(
