rtl/fifo.v
module fifo #(  parameter DATA_WIDTH = 8 ,
                parameter DEPTH = 16)(
                    input wire clk,
                    input wire rst,

                    input wire wr_en,
                    input wire rd_en,

                    input wire [DATA_WIDTH-1:0] din,

                    output reg [DATA_WIDTH-1:0] dout,
                    
                    output wire full,
                    output wire empty,

                    output reg overflow,
                    output reg underflow

                );
    /*
        INTERNAL MEMORY
    */
    
    reg [DATA_WIDTH-1:0] memory [0:DEPTH-1];    
   
    /*
        INTERNAL REGISTERS
    */
    
    localparam ADDR_WIDTH = $clog2(DEPTH);

    reg [ADDR_WIDTH-1:0] wr_ptr;//write pointer
    reg [ADDR_WIDTH-1:0] rd_ptr;//read pointer

    reg [ADDR_WIDTH:0] count;

    /*
        NEXT STATE 
    */

    wire [ADDR_WIDTH-1:0] wr_ptr_next;
    wire [ADDR_WIDTH-1:0] rd_ptr_next;
    
    assign wr_ptr_next = (wr_ptr == DEPTH-1) ? 0 : wr_ptr + 1;
    assign rd_ptr_next = (rd_ptr == DEPTH-1) ? 0 : rd_ptr + 1;

    /*
        STATUS FLAGS
    */

    assign full = (count == DEPTH);
    assign empty = (count == 0);

    /*
        OPERATION ENABLE LOGIC
    */

    wire write_ok;
    wire read_ok;

    assign write_ok = wr_en && (!full || rd_en);
    assign read_ok  = rd_en && !empty;


    /*
        SEQUENTIAL LOGIC SECTION
    */
    always@(posedge clk) begin

        if (rst) begin

            wr_ptr <= 0;
            rd_ptr <= 0;
            count <= 0;

            dout <= 0;

            overflow <= 0;
            underflow <= 0;

        end
        else begin
            overflow <= 0;
            underflow <= 0;
            /*
                WRITE OPERATION
            */
            if (wr_en) begin
                if (write_ok) begin

                    memory[wr_ptr] <= din;
                    wr_ptr <= wr_ptr_next;

                end
                else if (wr_en) begin

                    overflow <= 1;

                end
            end
            /*
                READ OPERATION
            */
            if (rd_en) begin
                if (read_ok) begin

                    dout <= memory[rd_ptr];
                    rd_ptr <= rd_ptr_next;

                end
                else if (rd_en) begin

                    underflow <= 1;

                end
            end
            /*
                COUNT UPDATE
            */
            if (write_ok && !read_ok)
                count <= count + 1;
            else if (!write_ok && read_ok)
                count <= count - 1;
        end
    end

endmodule

tb/fifo_tb_simultaneous.v
    `timescale 1ns/1ps

    module fifo_tb_simultaneous;

        /*
            ALL DECLARATIONS
        */
        parameter DATA_WIDTH = 8;
        parameter DEPTH = 16;

        reg clk;
        reg rst;

        reg wr_en;
        reg rd_en;

        reg [DATA_WIDTH-1:0] din;

        wire [DATA_WIDTH-1:0] dout;
                        
        wire full;
        wire empty;

        wire overflow;
        wire underflow;

        fifo #(
            .DATA_WIDTH(DATA_WIDTH),
            .DEPTH(DEPTH)
        ) dut (

            .clk(clk),
            .rst(rst),

            .wr_en(wr_en),  
            .rd_en(rd_en),

            .din(din),
            .dout(dout),

            .full(full),
            .empty(empty),

            .overflow(overflow),
            .underflow(underflow)

        );

        integer i;

        task fifo_simultaneous_rw;

            input [DATA_WIDTH-1:0] data;
            begin
                #10;
                din = data;
                wr_en = 1;
                rd_en = 1;

                #10;
                wr_en = 0;
                rd_en = 0;
            end

        endtask

        initial begin
            clk = 0;
        end

        /*
            CLK GENERATION
        */
        always #5 clk = ~clk;
        /*
            RESET INITIATION
        */
        initial begin

            $dumpfile("wave/fifo_simulataneous.vcd");
            $dumpvars(0,fifo_tb_simultaneous);

            rst  = 1;
            wr_en = 0;
            rd_en = 0;
            din = 0;

            #20;//2 clk cycles

            rst = 0; 

            /* 
                WRITES FILL
            */

            for (i=0; i < DEPTH ;i++)begin
                #10;
                din = i;
                wr_en = 1;

                #10;
                wr_en = 0;
            end

            /*
                SIMULATANEOUS WRIE AND READ
            */
            
            fifo_simultaneous_rw(8'h66);
            fifo_simultaneous_rw(8'h77);
            
            //END
            #20;
            $finish;//signals would run forever otherwise

        end
        

    endmodule

wave/fifo_simulataneous.vcd
$date
	Mon Jul 13 21:42:11 2026
$end
$version
	Icarus Verilog
$end
$timescale
	1ps
$end
$scope module fifo_tb_simultaneous $end
$var wire 1 ! underflow $end
$var wire 1 " overflow $end
$var wire 1 # full $end
$var wire 1 $ empty $end
$var wire 8 % dout [7:0] $end
$var parameter 32 & DATA_WIDTH $end
$var parameter 32 ' DEPTH $end
$var reg 1 ( clk $end
$var reg 8 ) din [7:0] $end
$var reg 1 * rd_en $end
$var reg 1 + rst $end
$var reg 1 , wr_en $end
$var integer 32 - i [31:0] $end
$scope module dut $end
$var wire 1 ( clk $end
$var wire 8 . din [7:0] $end
$var wire 1 * rd_en $end
$var wire 1 / read_ok $end
$var wire 1 + rst $end
$var wire 1 , wr_en $end
$var wire 1 0 write_ok $end
$var wire 4 1 wr_ptr_next [3:0] $end
$var wire 4 2 rd_ptr_next [3:0] $end
$var wire 1 # full $end
$var wire 1 $ empty $end
$var parameter 32 3 ADDR_WIDTH $end
$var parameter 32 4 DATA_WIDTH $end
$var parameter 32 5 DEPTH $end
$var reg 5 6 count [4:0] $end
$var reg 8 7 dout [7:0] $end
$var reg 1 " overflow $end
$var reg 4 8 rd_ptr [3:0] $end
$var reg 1 ! underflow $end
$var reg 4 9 wr_ptr [3:0] $end
$upscope $end
$scope task fifo_simultaneous_rw $end
$var reg 8 : data [7:0] $end
$upscope $end
$upscope $end
$enddefinitions $end
$comment Show the parameter values. $end
$dumpall
b10000 5
b1000 4
b100 3
b10000 '
b1000 &
$end
#0
$dumpvars
bx :
bx 9
bx 8
bx 7
bx 6
bx 2
bx 1
00
0/
b0 .
bx -
0,
1+
0*
b0 )
0(
bx %
x$
x#
x"
x!
$end
#5000
b1 2
b1 1
0!
0"
b0 %
b0 7
0#
1$
b0 6
b0 8
b0 9
1(
#10000
0(
#15000
1(
#20000
0(
b0 -
0+
#25000
1(
#30000
10
0(
1,
#35000
b10 1
0$
b1 6
b1 9
1(
#40000
00
0(
b1 -
0,
#45000
1(
#50000
10
0(
1,
b1 )
b1 .
#55000
b11 1
b10 6
b10 9
1(
#60000
00
0(
b10 -
0,
#65000
1(
#70000
10
0(
1,
b10 )
b10 .
#75000
b100 1
b11 6
b11 9
1(
#80000
00
0(
b11 -
0,
#85000
1(
#90000
10
0(
1,
b11 )
b11 .
#95000
b101 1
b100 6
b100 9
1(
#100000
00
0(
b100 -
0,
#105000
1(
#110000
10
0(
1,
b100 )
b100 .
#115000
b110 1
b101 6
b101 9
1(
#120000
00
0(
b101 -
0,
#125000
1(
#130000
10
0(
1,
b101 )
b101 .
#135000
b111 1
b110 6
b110 9
1(
#140000
00
0(
b110 -
0,
#145000
1(
#150000
10
0(
1,
b110 )
b110 .
#155000
b1000 1
b111 6
b111 9
1(
#160000
00
0(
b111 -
0,
#165000
1(
#170000
10
0(
1,
b111 )
b111 .
#175000
b1001 1
b1000 6
b1000 9
1(
#180000
00
0(
b1000 -
0,
#185000
1(
#190000
10
0(
1,
b1000 )
b1000 .
#195000
b1010 1
b1001 6
b1001 9
1(
#200000
00
0(
b1001 -
0,
#205000
1(
#210000
10
0(
1,
b1001 )
b1001 .
#215000
b1011 1
b1010 6
b1010 9
1(
#220000
00
0(
b1010 -
0,
#225000
1(
#230000
10
0(
1,
b1010 )
b1010 .
#235000
b1100 1
b1011 6
b1011 9
1(
#240000
00
0(
b1011 -
0,
#245000
1(
#250000
10
0(
1,
b1011 )
b1011 .
#255000
b1101 1
b1100 6
b1100 9
1(
#260000
00
0(
b1100 -
0,
#265000
1(
#270000
10
0(
1,
b1100 )
b1100 .
#275000
b1110 1
b1101 6
b1101 9
1(
#280000
00
0(
b1101 -
0,
#285000
1(
#290000
10
0(
1,
b1101 )
b1101 .
#295000
b1111 1
b1110 6
b1110 9
1(
#300000
00
0(
b1110 -
0,
#305000
1(
#310000
10
0(
1,
b1110 )
b1110 .
#315000
b0 1
b1111 6
b1111 9
1(
#320000
00
0(
b1111 -
0,
#325000
1(
#330000
10
0(
1,
b1111 )
b1111 .
#335000
00
b1 1
1#
b10000 6
b0 9
1(
#340000
0(
b1100110 :
b10000 -
0,
#345000
1(
#350000
10
1/
0(
1*
1,
b1100110 )
b1100110 .
#355000
b10 2
b10 1
b1 8
b1 9
1(
#360000
0/
00
0(
b1110111 :
0*
0,
#365000
1(
#370000
10
1/
0(
1*
1,
b1110111 )
b1110111 .
#375000
b11 2
b11 1
b10 8
b1 %
b1 7
b10 9
1(
#380000
0/
00
0(
0*
0,
